dashboard_client.pypy37-pp73-win_amd64.pyd
rtde.dll
rtde_control.pypy37-pp73-win_amd64.pyd
rtde_io.pypy37-pp73-win_amd64.pyd
rtde_receive.pypy37-pp73-win_amd64.pyd
script_client.pypy37-pp73-win_amd64.pyd
urcl/default_log_handler.cpp
urcl/log.cpp
urcl/script_sender.cpp
urcl/tcp_server.cpp
urcl/tcp_socket.cpp
urcl/__init__.py
ur_rtde-1.6.2.data/platlib/.load-order-ur_rtde-1.6.2
ur_rtde-1.6.2.data/platlib/msvcp140-70f646a5f67949fda1eb4df221999405.dll
ur_rtde-1.6.2.data/platlib/vcruntime140_1-16d928582d8b2bf90217176aee394aa9.dll
ur_rtde-1.6.2.dist-info/DELVEWHEEL
ur_rtde-1.6.2.dist-info/LICENSE
ur_rtde-1.6.2.dist-info/METADATA
ur_rtde-1.6.2.dist-info/RECORD
ur_rtde-1.6.2.dist-info/top_level.txt
ur_rtde-1.6.2.dist-info/WHEEL
