Metadata-Version: 2.1
Name: ur-rtde
Version: 1.6.2
Summary: A Python interface for controlling and receiving data from a UR robot using the Real-Time Data Exchange (RTDE) interface of the robot.
Home-page: https://gitlab.com/sdurobotics/ur_rtde
Author: Anders Prier Lindvig
Author-email: Anders Prier Lindvig <anpl@mmmi.sdu.dk>
Maintainer-email: Anders Prier Lindvig <anpl@mmmi.sdu.dk>
License: MIT License
Project-URL: Homepage, https://gitlab.com/sdurobotics/ur_rtde
Project-URL: Documentation, https://sdurobotics.gitlab.io/ur_rtde/
Project-URL: Repository, https://gitlab.com/sdurobotics/ur_rtde.git
Classifier: Programming Language :: Python :: 3
Classifier: License :: OSI Approved :: MIT License
Classifier: Operating System :: OS Independent
License-File: LICENSE
